dbt_metric_utils/__init__.py
dbt_metric_utils/cli.py
dbt_metric_utils/dbt_metric_utils_materialize.sql
dbt_metric_utils/materialize_metrics.py
dbt_metric_utils_custom-0.1.3.dist-info/METADATA
dbt_metric_utils_custom-0.1.3.dist-info/WHEEL
dbt_metric_utils_custom-0.1.3.dist-info/entry_points.txt
dbt_metric_utils_custom-0.1.3.dist-info/licenses/LICENSE.md
dbt_metric_utils_custom-0.1.3.dist-info/RECORD
