Metadata-Version: 2.3
Name: dbt-metric-utils-custom
Version: 0.1.3
Summary: Utilities for dbt metrics.
Author-email: Diederik Jan Lemkes <dj.lemkes@gmail.com>
License-File: LICENSE.md
Requires-Python: >=3.10
Requires-Dist: click>=7.1
Requires-Dist: dbt-core>=1.6.0
Requires-Dist: dbt-metricflow>=0.6.0
Requires-Dist: yaspin>=2
